tt_augment/__init__.py
tt_augment/augment.py
tt_augment/tt_custom/__init__.py
tt_augment/tt_custom/custom.py
tt_augment/tt_custom/tt_fwd_bkd.py
ttAugment-0.4.1.dist-info/LICENSE
ttAugment-0.4.1.dist-info/METADATA
ttAugment-0.4.1.dist-info/WHEEL
ttAugment-0.4.1.dist-info/top_level.txt
ttAugment-0.4.1.dist-info/RECORD
