Metadata-Version: 2.1
Name: ttAugment
Version: 0.4.1
Summary: Test Time Augmentations
Author: Fuzail Palnak
Author-email: fuzailpalnak@gmail.com
Keywords: Deep Learning Inference,PyTorch,Augmentations,TensorFlow
Classifier: Programming Language :: Python :: 3
Classifier: License :: OSI Approved :: MIT License
Classifier: Operating System :: OS Independent
Requires-Python: ~=3.6
License-File: LICENSE
Requires-Dist: imgaug (==0.4.0)
Requires-Dist: numpy (==1.19.1)
Requires-Dist: image-fragment (==0.2.2)
Requires-Dist: py-oneliner (==0.0.1)
